django_wheatgrass_blog-0.1.dist-info/DESCRIPTION.rst
django_wheatgrass_blog-0.1.dist-info/METADATA
django_wheatgrass_blog-0.1.dist-info/RECORD
django_wheatgrass_blog-0.1.dist-info/WHEEL
django_wheatgrass_blog-0.1.dist-info/metadata.json
django_wheatgrass_blog-0.1.dist-info/top_level.txt
tests/__init__.py
tests/urls.py
wheatgrass_blog/__init__.py
wheatgrass_blog/admin.py
wheatgrass_blog/api.py
wheatgrass_blog/apps.py
wheatgrass_blog/forms.py
wheatgrass_blog/models.py
wheatgrass_blog/tests.py
wheatgrass_blog/urls.py
wheatgrass_blog/views.py
wheatgrass_blog/management/__init__.py
wheatgrass_blog/management/commands/__init__.py
wheatgrass_blog/management/commands/remove_blank_articles.py
wheatgrass_blog/management/commands/remove_inaccessible_files.py
wheatgrass_blog/migrations/0001_initial.py
wheatgrass_blog/migrations/__init__.py
wheatgrass_blog/static/wheatgrass_blog/css/forms.css
wheatgrass_blog/static/wheatgrass_blog/css/setup.css
wheatgrass_blog/static/wheatgrass_blog/css/components/article-form.css
wheatgrass_blog/static/wheatgrass_blog/css/components/article-list.css
wheatgrass_blog/static/wheatgrass_blog/css/components/article-page.css
wheatgrass_blog/static/wheatgrass_blog/css/components/article.css
wheatgrass_blog/static/wheatgrass_blog/img/article-file-placeholder.png
wheatgrass_blog/static/wheatgrass_blog/img/article-thumbnail-placeholder.png
wheatgrass_blog/static/wheatgrass_blog/js/scripts.js
wheatgrass_blog/static/wheatgrass_blog/js/components/article.js
wheatgrass_blog/static/wheatgrass_blog/third-party/css/dropzone-basic.min.css
wheatgrass_blog/static/wheatgrass_blog/third-party/css/dropzone.min.css
wheatgrass_blog/static/wheatgrass_blog/third-party/js/clipboard.min.js
wheatgrass_blog/static/wheatgrass_blog/third-party/js/dropzone.min.js
wheatgrass_blog/static/wheatgrass_blog/third-party/js/js.cookie.js
wheatgrass_blog/templates/base/base.html
wheatgrass_blog/templates/base/head.html
wheatgrass_blog/templates/base/misc.html
wheatgrass_blog/templates/wheatgrass_blog/article-create.html
wheatgrass_blog/templates/wheatgrass_blog/article-edit.html
wheatgrass_blog/templates/wheatgrass_blog/article-list.html
wheatgrass_blog/templates/wheatgrass_blog/article.html
wheatgrass_blog/utils/__init__.py
