Metadata-Version: 2.0
Name: django-wheatgrass-blog
Version: 0.1
Summary: django-wheatgrass-blog is a simple blogging platform designed for the Django Web Framework.
Home-page: https://github.com/FractionalFunction/django-wheatgrass-blog
Author: Richie Zhang
Author-email: UNKNOWN
License: MIT
Requires-Dist: Markdown (>=2.6.8)
Requires-Dist: django-crispy-forms (>=1.6.1)
Requires-Dist: django-import-export (>=0.5.1)
